pysktb/__init__.py
pysktb/__version__.py
pysktb/_params.py
pysktb/atom.py
pysktb/hamiltonian.py
pysktb/jit_modules.py
pysktb/lattice.py
pysktb/structure.py
pysktb/system.py
pysktb/utils/__init__.py
pysktb/utils/energitics.py
pysktb-0.5.6.dist-info/METADATA
pysktb-0.5.6.dist-info/WHEEL
pysktb-0.5.6.dist-info/top_level.txt
pysktb-0.5.6.dist-info/RECORD
