Metadata-Version: 2.1
Name: pysktb
Version: 0.5.6
Summary: Scientific Python package for solving Slater Koster tight-binding topological hamiltonian
Home-page: https://github.com/santoshkumarradha/pysktb
Author: Santosh Kumar Radha
Author-email: srr70@case.edu
License: MIT
Classifier: License :: OSI Approved :: MIT License
Classifier: Programming Language :: Python
Classifier: Programming Language :: Python :: 3
Classifier: Programming Language :: Python :: 3.6
Classifier: Programming Language :: Python :: Implementation :: CPython
Classifier: Programming Language :: Python :: Implementation :: PyPy
Requires-Python: >=3.6.0
Requires-Dist: joblib (==1.2.0)
Requires-Dist: numba (>=0.49.0)
Requires-Dist: pymatgen (>=2020.4.29)
Requires-Dist: numpy (>=1.18.3)
Requires-Dist: matplotlib (>=3.1.3)
Requires-Dist: scipy (>=1.2.1)
